clarena/__init__.py
clarena/cli.py
clarena/backbones/__init__.py
clarena/backbones/base.py
clarena/backbones/constants.py
clarena/backbones/mlp.py
clarena/backbones/resnet.py
clarena/callbacks/__init__.py
clarena/callbacks/cl_rich_progress_bar.py
clarena/callbacks/pylogger.py
clarena/callbacks/save_first_batch_images.py
clarena/callbacks/save_models.py
clarena/cl_algorithms/__init__.py
clarena/cl_algorithms/adahat.py
clarena/cl_algorithms/amnesiac_hat.py
clarena/cl_algorithms/base.py
clarena/cl_algorithms/cbp.py
clarena/cl_algorithms/ewc.py
clarena/cl_algorithms/fgadahat.py
clarena/cl_algorithms/finetuning.py
clarena/cl_algorithms/fix.py
clarena/cl_algorithms/hat.py
clarena/cl_algorithms/independent.py
clarena/cl_algorithms/lwf.py
clarena/cl_algorithms/nispa.py
clarena/cl_algorithms/random.py
clarena/cl_algorithms/wsn.py
clarena/cl_algorithms/regularizers/__init__.py
clarena/cl_algorithms/regularizers/distillation.py
clarena/cl_algorithms/regularizers/hat_mask_sparsity.py
clarena/cl_algorithms/regularizers/parameter_change.py
clarena/cl_datasets/__init__.py
clarena/cl_datasets/base.py
clarena/cl_datasets/combined.py
clarena/cl_datasets/permuted_SEMEION.py
clarena/cl_datasets/permuted_ahdd.py
clarena/cl_datasets/permuted_caltech101.py
clarena/cl_datasets/permuted_caltech256.py
clarena/cl_datasets/permuted_celeba.py
clarena/cl_datasets/permuted_cifar10.py
clarena/cl_datasets/permuted_cifar100.py
clarena/cl_datasets/permuted_country211.py
clarena/cl_datasets/permuted_cub2002011.py
clarena/cl_datasets/permuted_dtd.py
clarena/cl_datasets/permuted_emnist.py
clarena/cl_datasets/permuted_eurosat.py
clarena/cl_datasets/permuted_facescrub.py
clarena/cl_datasets/permuted_fashionmnist.py
clarena/cl_datasets/permuted_fer2013.py
clarena/cl_datasets/permuted_fgvc_aircraft.py
clarena/cl_datasets/permuted_flowers102.py
clarena/cl_datasets/permuted_food101.py
clarena/cl_datasets/permuted_gtsrb.py
clarena/cl_datasets/permuted_imagenette.py
clarena/cl_datasets/permuted_kannadamnist.py
clarena-1.1.0.dist-info/licenses/LICENSE
clarena-1.1.0.dist-info/METADATA
clarena-1.1.0.dist-info/WHEEL
clarena-1.1.0.dist-info/entry_points.txt
clarena-1.1.0.dist-info/top_level.txt
clarena-1.1.0.dist-info/RECORD
