Metadata-Version: 2.4
Name: clarena
Version: 1.1.0
Summary: An open-source machine learning package for continual learning research
Author-email: Pengxiang Wang <wangpengxiang@stu.pku.edu.cn>
Maintainer-email: Pengxiang Wang <wangpengxiang@stu.pku.edu.cn>
License: MIT License
Project-URL: Homepage, https://pengxiang-wang.com/projects/continual-learning-arena/
Project-URL: Bug Reports, https://github.com/pengxiang-wang/continual-learning-arena/issues
Project-URL: Funding, https://www.patreon.com/pxwang
Project-URL: Say Thanks!, https://github.com/pengxiang-wang/continual-learning-arena/discussions
Project-URL: Source, https://github.com/pengxiang-wang/continual-learning-arena/
Keywords: continual learning,machine learning,deep learning,artificial intelligence
Classifier: Programming Language :: Python :: 3
Classifier: License :: OSI Approved :: MIT License
Classifier: Operating System :: OS Independent
Classifier: Topic :: Scientific/Engineering :: Artificial Intelligence
Requires-Python: >=3.10
License-File: LICENSE
Requires-Dist: lightning>=2.4.0
Requires-Dist: hydra-core>=1.3
Requires-Dist: torchvision>=0.19.0
Requires-Dist: torchmetrics
Requires-Dist: captum
Requires-Dist: tensorboard
Requires-Dist: wandb
Requires-Dist: pandas
Requires-Dist: matplotlib
Requires-Dist: pyrootutils
Requires-Dist: hydra-colorlog
Requires-Dist: rich
Requires-Dist: psutil
Requires-Dist: typer
Requires-Dist: gdown
Requires-Dist: scipy
Requires-Dist: tinyimagenet
Requires-Dist: rarfile
Dynamic: license-file
